jorgesomas2/__init__.py
jorgesomas2/soma.py
jorgesomas2-0.1.dist-info/LICENSE
jorgesomas2-0.1.dist-info/METADATA
jorgesomas2-0.1.dist-info/WHEEL
jorgesomas2-0.1.dist-info/top_level.txt
jorgesomas2-0.1.dist-info/RECORD
