Metadata-Version: 2.1
Name: jorgesomas2
Version: 0.1
Summary: Pacote simples de soma
Home-page: 
Author: Jorge Luis
License: MIT
License-File: LICENSE
